scraper/__init__.py
tijori-0.1.0.dist-info/LICENSE
tijori-0.1.0.dist-info/METADATA
tijori-0.1.0.dist-info/WHEEL
tijori-0.1.0.dist-info/top_level.txt
tijori-0.1.0.dist-info/RECORD
